trectools/__init__.py
trectools/fusion.py
trectools/misc.py
trectools/procedures.py
trectools/trec_eval.py
trectools/trec_indri.py
trectools/trec_pisa.py
trectools/trec_pool.py
trectools/trec_pool_maker.py
trectools/trec_qrel.py
trectools/trec_res.py
trectools/trec_run.py
trectools/trec_terrier.py
trectools/trec_topics.py
trectools-0.0.45.dist-info/METADATA
trectools-0.0.45.dist-info/WHEEL
trectools-0.0.45.dist-info/top_level.txt
trectools-0.0.45.dist-info/RECORD
