Metadata-Version: 2.1
Name: trectools
Version: 0.0.45
Summary: An open-source Python library for assisting Information Retrieval (IR) practitioners with TREC-like campaigns.
Home-page: https://github.com/joaopalotti/trec_tools
Author: Joao Palotti
Author-email: joaopalotti@gmail.com
License: BSD
Platform: UNKNOWN
Requires-Dist: pandas (>=0.15.0)
Requires-Dist: numpy (>=1.0.0)
Requires-Dist: scikit-learn (>=0.15)
Requires-Dist: scipy (>=0.10.0)
Requires-Dist: sarge (>=0.1.1)
Requires-Dist: lxml (>=3.6.0)
Requires-Dist: bs4 (>=0.0.0.1)
Requires-Dist: matplotlib (>=1.5)
